PyNomaly/__init__.py
PyNomaly/loop.py
PyNomaly-0.3.4.dist-info/LICENSE.txt
PyNomaly-0.3.4.dist-info/METADATA
PyNomaly-0.3.4.dist-info/WHEEL
PyNomaly-0.3.4.dist-info/top_level.txt
PyNomaly-0.3.4.dist-info/RECORD
